ai_flow/__init__.py
ai_flow/__main__.py
ai_flow/alembic.ini
ai_flow/settings.py
ai_flow/version.py
ai_flow/ai_graph/__init__.py
ai_flow/ai_graph/ai_graph.py
ai_flow/ai_graph/ai_node.py
ai_flow/ai_graph/data_edge.py
ai_flow/api/__init__.py
ai_flow/api/ai_flow_context.py
ai_flow/api/context_extractor.py
ai_flow/api/ops.py
ai_flow/api/workflow_operation.py
ai_flow/cli/__init__.py
ai_flow/cli/cli_parser.py
ai_flow/cli/simple_table.py
ai_flow/cli/commands/__init__.py
ai_flow/cli/commands/config_command.py
ai_flow/cli/commands/db_command.py
ai_flow/cli/commands/job_command.py
ai_flow/cli/commands/server_command.py
ai_flow/cli/commands/version_command.py
ai_flow/cli/commands/webserver_command.py
ai_flow/cli/commands/workflow_command.py
ai_flow/client/__init__.py
ai_flow/client/ai_flow_client.py
ai_flow/client/notification_client.py
ai_flow/common/__init__.py
ai_flow/common/args.py
ai_flow/common/configuration.py
ai_flow/common/entity.py
ai_flow/common/message_queue.py
ai_flow/common/module_load.py
ai_flow/common/properties.py
ai_flow/common/registry.py
ai_flow/common/result.py
ai_flow/common/scheduler_type.py
ai_flow/common/status.py
ai_flow/config_templates/__init__.py
ai_flow/config_templates/default_aiflow_server.yaml
ai_flow/config_templates/__pycache__/__init__.cpython-37.pyc
ai_flow/context/__init__.py
ai_flow/context/job_context.py
ai_flow/context/project_context.py
ai_flow/context/workflow_config_loader.py
ai_flow/endpoint/__init__.py
ai_flow/endpoint/client/__init__.py
ai_flow/endpoint/client/base_client.py
ai_flow/endpoint/client/metadata_client.py
ai_flow/endpoint/client/metric_client.py
ai_flow/endpoint/client/model_center_client.py
ai_flow/endpoint/client/scheduler_client.py
ai_flow/endpoint/server/__init__.py
ai_flow/endpoint/server/exception.py
ai_flow/endpoint/server/high_availability.py
ai_flow/endpoint/server/server.py
ai_flow/endpoint/server/server_config.py
ai_flow/endpoint/server/server_runner.py
ai_flow/endpoint/server/util.py
ai_flow-0.3.1.dist-info/LICENSE
ai_flow-0.3.1.dist-info/METADATA
ai_flow-0.3.1.dist-info/NOTICE
ai_flow-0.3.1.dist-info/WHEEL
ai_flow-0.3.1.dist-info/entry_points.txt
ai_flow-0.3.1.dist-info/top_level.txt
ai_flow-0.3.1.dist-info/RECORD
