Metadata-Version: 2.1
Name: ai-flow
Version: 0.3.1
Summary: An open source framework that bridges big data and AI.
Home-page: https://github.com/flink-extended/ai-flow
Author: 
Author-email: flink.aiflow@gmail.com
License: UNKNOWN
Platform: UNKNOWN
Requires-Python: >=3.7, <3.8
Requires-Dist: notification-service (==0.3.1)
Requires-Dist: streamz (==0.5.2)
Requires-Dist: matplotlib (==3.1.2)
Requires-Dist: grpcio (==1.35.0)
Requires-Dist: requests (==2.22.0)
Requires-Dist: six (==1.12.0)
Requires-Dist: kafka-python (==2.0.2)
Requires-Dist: kubernetes (==9.0.0)
Requires-Dist: networkx (==2.4)
Requires-Dist: pika (==1.1.0)
Requires-Dist: protobuf (==3.15.6)
Requires-Dist: pyyaml (<5.4,>=5.1)
Requires-Dist: apscheduler (==3.6.3)
Requires-Dist: google-api-core (==1.16.0)
Requires-Dist: psutil (==5.6.3)
Requires-Dist: pyecharts (==1.8.1)
Requires-Dist: cloudpickle (==1.2.2)
Requires-Dist: flask (<2.0,>=1.1.0)
Requires-Dist: flask-admin (==1.5.4)
Requires-Dist: flask-caching (~=1.9.0)
Requires-Dist: flask-cors (>=3.0.10)
Requires-Dist: flask-login (<0.5,>=0.3)
Requires-Dist: flask-swagger (==0.2.13)
Requires-Dist: flask-wtf (<0.15,>=0.14.2)
Requires-Dist: Django (~=3.2.7)
Requires-Dist: WTForms (==2.3.3)
Requires-Dist: mongoengine (~=0.22.1)
Requires-Dist: alembic (<2.0,>=1.0)
Requires-Dist: argcomplete (~=1.10)
Requires-Dist: attrs (~=20.3.0)
Requires-Dist: cached-property (~=1.5)
Requires-Dist: cattrs (~=1.1.2)
Requires-Dist: colorlog (==4.0.2)
Requires-Dist: configparser (<3.6.0,>=3.5.0)
Requires-Dist: croniter (<0.4,>=0.3.17)
Requires-Dist: dill (<0.4,>=0.2.2)
Requires-Dist: funcsigs (<2.0.0,>=1.0.0)
Requires-Dist: future (<0.19,>=0.16.0)
Requires-Dist: graphviz (>=0.12)
Requires-Dist: gunicorn (<20.0,>=19.5.0)
Requires-Dist: iso8601 (>=0.1.12)
Requires-Dist: jinja2 (<2.11.0,>=2.10.1)
Requires-Dist: json-merge-patch (==0.2)
Requires-Dist: jsonschema (~=3.0)
Requires-Dist: lazy-object-proxy (~=1.3)
Requires-Dist: markdown (<3.0,>=2.5.2)
Requires-Dist: pendulum (~=2.0)
Requires-Dist: pygments (<3.0,>=2.0.1)
Requires-Dist: python-daemon (<2.2,>=2.1.1)
Requires-Dist: python-dateutil (<3,>=2.3)
Requires-Dist: setproctitle (<2,>=1.1.8)
Requires-Dist: sqlalchemy (==1.3.23)
Requires-Dist: tabulate (<0.9,>=0.7.5)
Requires-Dist: tenacity (==6.2.0)
Requires-Dist: termcolor (==1.1.0)
Requires-Dist: text-unidecode (==1.3)
Requires-Dist: thrift (>=0.9.2)
Requires-Dist: tzlocal (<2.0.0,>=1.4)
Requires-Dist: unicodecsv (>=0.14.1)
Requires-Dist: werkzeug (~=1.0)
Requires-Dist: zope.deprecation (<5.0,>=4.0)
Requires-Dist: apache-airflow (==2.0.0)
Requires-Dist: apache-airflow-providers-ftp (==1.1.0)
Requires-Dist: apache-airflow-providers-http (==1.1.1)
Requires-Dist: apache-airflow-providers-imap (==1.0.1)
Requires-Dist: apache-airflow-providers-sqlite (==1.0.2)
Requires-Dist: enum34 (~=1.1.6) ; python_version < "3.4"
Requires-Dist: sqlalchemy-jsonfield (==0.8.0) ; python_version < "3.5"
Requires-Dist: typing ; python_version < "3.5"
Requires-Dist: flask-appbuilder (<2.0.0,>=1.12.2) ; python_version < "3.6"
Requires-Dist: marshmallow-sqlalchemy (<0.19.0,>=0.16.1) ; python_version < "3.6"
Requires-Dist: typing-extensions (>=3.7.4) ; python_version < "3.8"
Requires-Dist: sqlalchemy-jsonfield (~=1.0) ; python_version >= "3.5"
Requires-Dist: flask-appbuilder (~=3.1.1) ; python_version >= "3.6"
Provides-Extra: celery
Requires-Dist: apache-airflow-providers-celery (==1.0.1) ; extra == 'celery'
Requires-Dist: redis (~=3.2) ; extra == 'celery'
Provides-Extra: devel
Requires-Dist: coverage (>=6.1.1) ; extra == 'devel'
Requires-Dist: flake8 ; extra == 'devel'
Requires-Dist: pytest ; extra == 'devel'
Requires-Dist: mock ; extra == 'devel'
Requires-Dist: mongoengine (~=0.22.1) ; extra == 'devel'
Requires-Dist: pymysql (==0.9.3) ; extra == 'devel'
Requires-Dist: mysqlclient (<1.4,>=1.3.6) ; extra == 'devel'
Requires-Dist: oss2 (==2.9.1) ; extra == 'devel'
Requires-Dist: boto3 (~=1.19.7) ; extra == 'devel'
Requires-Dist: botocore (~=1.22.7) ; extra == 'devel'
Requires-Dist: hdfs (~=2.6.0) ; extra == 'devel'
Requires-Dist: apache-flink (==1.12.5) ; extra == 'devel'
Provides-Extra: example_requires
Requires-Dist: joblib (==1.0.1) ; extra == 'example_requires'
Requires-Dist: numpy (==1.18.1) ; extra == 'example_requires'
Requires-Dist: pandas (==0.24.2) ; extra == 'example_requires'
Requires-Dist: scikit-learn (==0.21.2) ; extra == 'example_requires'
Provides-Extra: hdfs
Requires-Dist: hdfs (~=2.6.0) ; extra == 'hdfs'
Provides-Extra: mongo
Requires-Dist: mongoengine (~=0.22.1) ; extra == 'mongo'
Provides-Extra: mysql
Requires-Dist: pymysql (==0.9.3) ; extra == 'mysql'
Requires-Dist: mysqlclient (<1.4,>=1.3.6) ; extra == 'mysql'
Provides-Extra: oss
Requires-Dist: oss2 (==2.9.1) ; extra == 'oss'
